{
    "external_dependencies":  [
                                  "bayesplot",
                                  "brms",
                                  "dplyr",
                                  "generics",
                                  "ggplot2",
                                  "insight",
                                  "loo",
                                  "magrittr",
                                  "marginaleffects",
                                  "methods",
                                  "mgcv",
                                  "mvnfast",
                                  "patchwork",
                                  "posterior",
                                  "purrr",
                                  "Rcpp",
                                  "rlang",
                                  "rstan",
                                  "rstantools",
                                  "tibble"
                              ],
    "generated":  "2025-10-21 17:11:37",
    "commit_hash":  "",
    "cached_files":  51,
    "version":  "2.0.0",
    "commit_message":  "",
    "unanalyzed_functions":  0,
    "total_functions":  468,
    "exported_functions":  56,
    "s3_methods_count":  40,
    "s3_classes_count":  28,
    "dynamic_references":  32,
    "package_name":  "mvgam",
    "potentially_unused_functions":  33,
    "changed_files":  6,
    "total_files":  57,
    "zero_dependency_functions":  379
}
